build/lib/build/lib/build/lib/build/lib/build/lib/computation_graph/__init__.py
build/lib/build/lib/build/lib/build/lib/build/lib/computation_graph/base_types.py
build/lib/build/lib/build/lib/build/lib/build/lib/computation_graph/graph.py
build/lib/build/lib/build/lib/build/lib/build/lib/computation_graph/graph_runners.py
build/lib/build/lib/build/lib/build/lib/build/lib/computation_graph/graph_test.py
build/lib/build/lib/build/lib/build/lib/build/lib/computation_graph/legacy.py
build/lib/build/lib/build/lib/build/lib/build/lib/computation_graph/run.py
build/lib/build/lib/build/lib/build/lib/build/lib/computation_graph/signature.py
build/lib/build/lib/build/lib/build/lib/build/lib/computation_graph/composers/__init__.py
build/lib/build/lib/build/lib/build/lib/build/lib/computation_graph/composers/composers_test.py
build/lib/build/lib/build/lib/build/lib/build/lib/computation_graph/composers/condition.py
build/lib/build/lib/build/lib/build/lib/build/lib/computation_graph/composers/condition_test.py
build/lib/build/lib/build/lib/build/lib/build/lib/computation_graph/composers/debug.py
build/lib/build/lib/build/lib/build/lib/build/lib/computation_graph/composers/duplication.py
build/lib/build/lib/build/lib/build/lib/build/lib/computation_graph/composers/lift.py
build/lib/build/lib/build/lib/build/lib/build/lib/computation_graph/composers/logic.py
build/lib/build/lib/build/lib/build/lib/build/lib/computation_graph/composers/memory.py
build/lib/build/lib/build/lib/build/lib/build/lib/computation_graph/composers/memory_test.py
build/lib/build/lib/build/lib/build/lib/build/lib/computation_graph/trace/__init__.py
build/lib/build/lib/build/lib/build/lib/build/lib/computation_graph/trace/ascii.py
build/lib/build/lib/build/lib/build/lib/build/lib/computation_graph/trace/graphviz.py
build/lib/build/lib/build/lib/build/lib/build/lib/computation_graph/trace/graphviz_test.py
build/lib/build/lib/build/lib/build/lib/build/lib/computation_graph/trace/mermaid.py
computation_graph-39.dist-info/LICENSE.md
computation_graph-39.dist-info/METADATA
computation_graph-39.dist-info/WHEEL
computation_graph-39.dist-info/top_level.txt
computation_graph-39.dist-info/RECORD
