Metadata-Version: 2.1
Name: computation-graph
Version: 39
Summary: UNKNOWN
Home-page: UNKNOWN
License: UNKNOWN
Platform: UNKNOWN
Requires-Python: >=3
License-File: LICENSE.md
Requires-Dist: gamla
Requires-Dist: typeguard
Requires-Dist: toposort
Requires-Dist: immutables
Requires-Dist: termcolor
Provides-Extra: test
Requires-Dist: pygraphviz ; extra == 'test'
Requires-Dist: pytest (>=5.4.0) ; extra == 'test'
